MANIFEST.in
README.txt
setup.py
docs/HISTORY.txt
docs/LICENSE.txt
src/silva/__init__.py
src/silva.pas.openid.egg-info/PKG-INFO
src/silva.pas.openid.egg-info/SOURCES.txt
src/silva.pas.openid.egg-info/dependency_links.txt
src/silva.pas.openid.egg-info/namespace_packages.txt
src/silva.pas.openid.egg-info/not-zip-safe
src/silva.pas.openid.egg-info/requires.txt
src/silva.pas.openid.egg-info/top_level.txt
src/silva/pas/__init__.py
src/silva/pas/openid/SilvaOpenIDMember.py
src/silva/pas/openid/__init__.py
src/silva/pas/openid/adapters.py
src/silva/pas/openid/configure.zcml
src/silva/pas/openid/events.py
src/silva/pas/openid/install.py
src/silva/pas/openid/interfaces.py
src/silva/pas/openid/store.py
src/silva/pas/openid/subscribers.py
src/silva/pas/openid/utilities.py
src/silva/pas/openid/views.py
src/silva/pas/openid/plugins/__init__.py
src/silva/pas/openid/plugins/oid.py
src/silva/pas/openid/static/openid-icon.png
src/silva/pas/openid/static/openid.css
src/silva/pas/openid/tests/__init__.py
src/silva/pas/openid/tests/test_service.py
src/silva/pas/openid/views_templates/loginpage.cpt
src/silva/pas/openid/views_templates/registerpage.cpt
src/silva/pas/openid/www/member.png
src/silva/pas/openid/www/openIDAddForm.zpt
src/silva/pas/openid/www/openIDMemberAdd.zpt
src/silva/pas/openid/www/openIDMemberDetails.zpt
src/silva/pas/openid/www/openid.png