Metadata-Version: 1.1
Name: silva.pas.openid
Version: 3.0
Summary: OpenID suport for Silva CMS
Home-page: https://github.com/silvacms/silva.pas.openid
Author: Sylvain Viollon
Author-email: info@infrae.com
License: BSD
Keywords: pas openid silva
Platform: UNKNOWN
Classifier: Framework :: Zope2
Classifier: Programming Language :: Python
Classifier: Topic :: Software Development :: Libraries :: Python Modules
Classifier: License :: OSI Approved :: BSD License
